{
  "headline": {
    "naive_overall_degraded_silent_k": 36,
    "naive_overall_degraded_silent_n": 164,
    "naive_overall_degraded_silent_rate": 0.21951219512195122,
    "naive_overall_degraded_silent_wilson_low": 0.16298304128303545,
    "naive_overall_degraded_silent_wilson_high": 0.2888810972857103
  },
  "rows": [
    {
      "panel": "primary_exact_retention_match",
      "pair_id": "A",
      "label": "naive@0.7",
      "method": "naive",
      "budget": 0.7,
      "n_total": 60,
      "n_degraded": 51,
      "n_strong": 9,
      "mean_achieved_retention": 0.6868589743589746,
      "pivot_accuracy": 0.8,
      "pivot_preservation": 0.6,
      "info_shift_rate": 0.4,
      "silent_mirage_count": 12,
      "silent_mirage_n": 51,
      "silent_mirage_rate": 0.23529411764705882,
      "silent_mirage_wilson_low": 0.14004812598862515,
      "silent_mirage_wilson_high": 0.36762488136345783,
      "flag_degraded_rate": 0.0,
      "flag_given_wrong": 0.0,
      "flag_given_wrong_wilson_low": 0.0,
      "flag_given_wrong_wilson_high": 0.2425007574992425
    },
    {
      "panel": "primary_exact_retention_match",
      "pair_id": "A",
      "label": "contract@0.7",
      "method": "contract",
      "budget": 0.7,
      "n_total": 60,
      "n_degraded": 4,
      "n_strong": 56,
      "mean_achieved_retention": 0.6868589743589746,
      "pivot_accuracy": 1.0,
      "pivot_preservation": 1.0,
      "info_shift_rate": 0.0,
      "silent_mirage_count": 0,
      "silent_mirage_n": 4,
      "silent_mirage_rate": 0.0,
      "silent_mirage_wilson_low": 0.0,
      "silent_mirage_wilson_high": 0.48990002040399916,
      "flag_degraded_rate": 0.0,
      "flag_given_wrong": null,
      "flag_given_wrong_wilson_low": null,
      "flag_given_wrong_wilson_high": null
    },
    {
      "panel": "secondary_cross_budget_near_match",
      "pair_id": "B",
      "label": "naive@0.5",
      "method": "naive",
      "budget": 0.5,
      "n_total": 60,
      "n_degraded": 56,
      "n_strong": 4,
      "mean_achieved_retention": 0.4782763532763533,
      "pivot_accuracy": 0.8166666666666667,
      "pivot_preservation": 0.45,
      "info_shift_rate": 0.55,
      "silent_mirage_count": 11,
      "silent_mirage_n": 56,
      "silent_mirage_rate": 0.19642857142857142,
      "silent_mirage_wilson_low": 0.11338480016444108,
      "silent_mirage_wilson_high": 0.3184485732747718,
      "flag_degraded_rate": 0.0,
      "flag_given_wrong": 0.0,
      "flag_given_wrong_wilson_low": 2.7755575615628914e-17,
      "flag_given_wrong_wilson_high": 0.2588400172488141
    },
    {
      "panel": "secondary_cross_budget_near_match",
      "pair_id": "B",
      "label": "contract@0.3",
      "method": "contract",
      "budget": 0.3,
      "n_total": 60,
      "n_degraded": 10,
      "n_strong": 50,
      "mean_achieved_retention": 0.4505698005698005,
      "pivot_accuracy": 1.0,
      "pivot_preservation": 1.0,
      "info_shift_rate": 0.0,
      "silent_mirage_count": 0,
      "silent_mirage_n": 10,
      "silent_mirage_rate": 0.0,
      "silent_mirage_wilson_low": 0.0,
      "silent_mirage_wilson_high": 0.2775401687666165,
      "flag_degraded_rate": 0.0,
      "flag_given_wrong": null,
      "flag_given_wrong_wilson_low": null,
      "flag_given_wrong_wilson_high": null
    }
  ]
}
